xync_bot/__init__.py
xync_bot/__main__.py
xync_bot/loader.py
xync_bot/shared.py
xync_bot/store.py
xync_bot/typs.py
xync_bot/routers/__init__.py
xync_bot/routers/order.py
xync_bot/routers/photo.py
xync_bot/routers/vpn.py
xync_bot/routers/xicon.png
xync_bot/routers/cond/__init__.py
xync_bot/routers/cond/func.py
xync_bot/routers/hot/__init__.py
xync_bot/routers/main/__init__.py
xync_bot/routers/main/handler.py
xync_bot/routers/pay/cd.py
xync_bot/routers/pay/dep.py
xync_bot/routers/pay/handler.py
xync_bot/routers/pay/window.py
xync_bot/routers/send/__init__.py
xync_bot-0.3.53.dist-info/METADATA
xync_bot-0.3.53.dist-info/WHEEL
xync_bot-0.3.53.dist-info/top_level.txt
xync_bot-0.3.53.dist-info/RECORD
