Metadata-Version: 2.4
Name: xync-bot
Version: 0.3.53
Summary: Telegram bot with web app for xync net
Author-email: Artemiev <mixartemev@gmail.com>
License-Expression: GPL-3.0-or-later
Project-URL: Homepage, https://gitlab.com/xync/back/tg-bot
Project-URL: Repository, https://gitlab.com/xync/back/tg-bot
Keywords: aiogram,cyrtranslit,xync-net
Requires-Python: >=3.12
Requires-Dist: cyrtranslit
Requires-Dist: xn-auth
Requires-Dist: xync-schema
Provides-Extra: dev
Requires-Dist: PGram; extra == "dev"
Requires-Dist: pre-commit; extra == "dev"
Requires-Dist: pytest; extra == "dev"
Requires-Dist: python-dotenv; extra == "dev"
Requires-Dist: setuptools-scm; extra == "dev"
Requires-Dist: build; extra == "dev"
Requires-Dist: twine; extra == "dev"
